README.md
setup.py
texbib/__init__.py
texbib/__main__.py
texbib/bibliography.py
texbib/cli.py
texbib/colors.py
texbib/commands.py
texbib/parser.py
texbib/runtime.py
texbib/schemes.py
texbib/term_utils.py
texbib/utils.py
texbib.egg-info/PKG-INFO
texbib.egg-info/SOURCES.txt
texbib.egg-info/dependency_links.txt
texbib.egg-info/entry_points.txt
texbib.egg-info/requires.txt
texbib.egg-info/top_level.txt
texbib/sources/__init__.py
texbib/sources/arxiv.py
texbib/sources/doi.py
texbib/sources/file.py
texbib/sources/isbn.py