Metadata-Version: 2.1
Name: texbib
Version: 0.3.1
Summary: A tool for managing bibliographies
Home-page: https://github.com/frcl/bib
Author: Lars Franke
Author-email: frcl@mailbox.org
License: GPLv3
Keywords: bibtex latex science writing
Platform: UNKNOWN
Classifier: Development Status :: 3 - Alpha
Classifier: Intended Audience :: Science/Research
Classifier: Environment :: Console
Classifier: Programming Language :: Python :: 3
Classifier: Programming Language :: Python :: 3.6
Classifier: Programming Language :: Python :: 3.7
Classifier: License :: OSI Approved :: GNU General Public License v3 (GPLv3)
Provides-Extra: test
